biao_maps/__init__.py
biao_maps/maps.py
biao_maps-0.0.1.dist-info/METADATA
biao_maps-0.0.1.dist-info/WHEEL
biao_maps-0.0.1.dist-info/licenses/LICENSE
biao_maps-0.0.1.dist-info/RECORD
