Metadata-Version: 2.3
Name: biao_maps
Version: 0.0.1
Summary: Metamask Automation with Python and Selenium
Project-URL: Source, https://github.com/BroBiao/MAPS
Project-URL: Repository, https://github.com/BroBiao/MAPS
Author-email: BroBiao <brobiao29@gmail.com>
Maintainer-email: BroBiao <brobiao29@gmail.com>
License: MIT License
License-File: LICENSE
Classifier: License :: OSI Approved :: MIT License
Classifier: Programming Language :: Python
Requires-Python: >=3.5
Requires-Dist: debiaosgs
Requires-Dist: eth-account
Requires-Dist: numpy
Requires-Dist: pandas
Requires-Dist: requests
Requires-Dist: selenium
Requires-Dist: web3
